[
 {
   "nivel": 1,
   "Sin Armadura (sa)": 15,
   "Cuero (cu)": 0,
   "Cuero Endurecido (ce)": 0,
   "Cota de Malla (cm)": -25,
   "Coraza (co)": -70,
   "Bonificación Defensiva": 15,
   "Arma principal": 43,
   "Arma secundaria": 28,
   "Arma terciaria": 33,
   "Arma cuarta": 28,
   "Trepar": 16,
   "Montar": 6,
   "Nadar": 16,
   "Rastrear": 6,
   "Emboscar": -25,
   "Acechar-Sigilo": 5,
   "Abrir Cerraduras": 5,
   "Desactivar Trampas": 5,
   "Leer Runas": -25,
   "Usar Objetos": -25,
   "Hechizos dirigidos": -15,
   "Percepción": 5,
   "totalPv": 34,
   "Hechizos básicos": 0,
   "Listas de hechizos": 0,
   "Oficio": 0,
   "name": "guerrero"
 },
 {
   "nivel": 2,
   "Sin Armadura (sa)": 15,
   "Cuero (cu)": 0,
   "Cuero Endurecido (ce)": 5,
   "Cota de Malla (cm)": -15,
   "Coraza (co)": -70,
   "Bonificación Defensiva": 15,
   "Arma principal": 56,
   "Arma secundaria": 36,
   "Arma terciaria": 41,
   "Arma cuarta": 31,
   "Trepar": 22,
   "Montar": 12,
   "Nadar": 17,
   "Rastrear": 7,
   "Emboscar": -25,
   "Acechar-Sigilo": 10,
   "Abrir Cerraduras": 5,
   "Desactivar Trampas": 5,
   "Leer Runas": -25,
   "Usar Objetos": -25,
   "Hechizos dirigidos": -15,
   "Percepción": 10,
   "totalPv": 47,
   "Hechizos básicos": 0,
   "Listas de hechizos": 0,
   "Oficio": 0,
   "name": "guerrero"
 },
 {
   "nivel": 3,
   "Sin Armadura (sa)": 15,
   "Cuero (cu)": 0,
   "Cuero Endurecido (ce)": 5,
   "Cota de Malla (cm)": 0,
   "Coraza (co)": -70,
   "Bonificación Defensiva": 15,
   "Arma principal": 69,
   "Arma secundaria": 44,
   "Arma terciaria": 49,
   "Arma cuarta": 34,
   "Trepar": 23,
   "Montar": 18,
   "Nadar": 18,
   "Rastrear": 13,
   "Emboscar": -25,
   "Acechar-Sigilo": 10,
   "Abrir Cerraduras": 10,
   "Desactivar Trampas": 10,
   "Leer Runas": -25,
   "Usar Objetos": -25,
   "Hechizos dirigidos": -15,
   "Percepción": 10,
   "totalPv": 60,
   "Hechizos básicos": 0,
   "Listas de hechizos": 0,
   "Oficio": 0,
   "name": "guerrero"
 },
 {
   "nivel": 4,
   "Sin Armadura (sa)": 15,
   "Cuero (cu)": 0,
   "Cuero Endurecido (ce)": 5,
   "Cota de Malla (cm)": 5,
   "Coraza (co)": -35,
   "Bonificación Defensiva": 15,
   "Arma principal": 82,
   "Arma secundaria": 52,
   "Arma terciaria": 57,
   "Arma cuarta": 37,
   "Trepar": 24,
   "Montar": 24,
   "Nadar": 19,
   "Rastrear": 14,
   "Emboscar": 1,
   "Acechar-Sigilo": 15,
   "Abrir Cerraduras": 10,
   "Desactivar Trampas": 10,
   "Leer Runas": -25,
   "Usar Objetos": -25,
   "Hechizos dirigidos": -15,
   "Percepción": 15,
   "totalPv": 73,
   "Hechizos básicos": 0,
   "Listas de hechizos": 0,
   "Oficio": 0,
   "name": "guerrero"
 },
 {
   "nivel": 5,
   "Sin Armadura (sa)": 15,
   "Cuero (cu)": 0,
   "Cuero Endurecido (ce)": 5,
   "Cota de Malla (cm)": 5,
   "Coraza (co)": -20,
   "Bonificación Defensiva": 15,
   "Arma principal": 95,
   "Arma secundaria": 60,
   "Arma terciaria": 65,
   "Arma cuarta": 40,
   "Trepar": 25,
   "Montar": 30,
   "Nadar": 20,
   "Rastrear": 20,
   "Emboscar": 1,
   "Acechar-Sigilo": 15,
   "Abrir Cerraduras": 15,
   "Desactivar Trampas": 15,
   "Leer Runas": -25,
   "Usar Objetos": -25,
   "Hechizos dirigidos": -15,
   "Percepción": 15,
   "totalPv": 86,
   "Hechizos básicos": 0,
   "Listas de hechizos": 0,
   "Oficio": 0,
   "name": "guerrero"
 },
 {
   "nivel": 6,
   "Sin Armadura (sa)": 15,
   "Cuero (cu)": 0,
   "Cuero Endurecido (ce)": 5,
   "Cota de Malla (cm)": 5,
   "Coraza (co)": -5,
   "Bonificación Defensiva": 15,
   "Arma principal": 100,
   "Arma secundaria": 73,
   "Arma terciaria": 73,
   "Arma cuarta": 43,
   "Trepar": 31,
   "Montar": 36,
   "Nadar": 21,
   "Rastrear": 21,
   "Emboscar": 1,
   "Acechar-Sigilo": 20,
   "Abrir Cerraduras": 15,
   "Desactivar Trampas": 15,
   "Leer Runas": -25,
   "Usar Objetos": -25,
   "Hechizos dirigidos": -15,
   "Percepción": 20,
   "totalPv": 99,
   "Hechizos básicos": 0,
   "Listas de hechizos": 0,
   "Oficio": 0,
   "name": "guerrero"
 },
 {
   "nivel": 7,
   "Sin Armadura (sa)": 15,
   "Cuero (cu)": 0,
   "Cuero Endurecido (ce)": 5,
   "Cota de Malla (cm)": 5,
   "Coraza (co)": 0,
   "Bonificación Defensiva": 15,
   "Arma principal": 105,
   "Arma secundaria": 86,
   "Arma terciaria": 81,
   "Arma cuarta": 46,
   "Trepar": 32,
   "Montar": 42,
   "Nadar": 22,
   "Rastrear": 27,
   "Emboscar": 1,
   "Acechar-Sigilo": 20,
   "Abrir Cerraduras": 20,
   "Desactivar Trampas": 20,
   "Leer Runas": 5,
   "Usar Objetos": -25,
   "Hechizos dirigidos": -15,
   "Percepción": 20,
   "totalPv": 106,
   "Hechizos básicos": 0,
   "Listas de hechizos": 0,
   "Oficio": 0,
   "name": "guerrero"
 },
 {
   "nivel": 8,
   "Sin Armadura (sa)": 20,
   "Cuero (cu)": 0,
   "Cuero Endurecido (ce)": 5,
   "Cota de Malla (cm)": 5,
   "Coraza (co)": 0,
   "Bonificación Defensiva": 15,
   "Arma principal": 110,
   "Arma secundaria": 91,
   "Arma terciaria": 94,
   "Arma cuarta": 49,
   "Trepar": 33,
   "Montar": 48,
   "Nadar": 23,
   "Rastrear": 28,
   "Emboscar": 2,
   "Acechar-Sigilo": 25,
   "Abrir Cerraduras": 20,
   "Desactivar Trampas": 20,
   "Leer Runas": 5,
   "Usar Objetos": 5,
   "Hechizos dirigidos": -15,
   "Percepción": 25,
   "totalPv": 114,
   "Hechizos básicos": 0,
   "Listas de hechizos": 0,
   "Oficio": 0,
   "name": "guerrero"
 },
 {
   "nivel": 9,
   "Sin Armadura (sa)": 20,
   "Cuero (cu)": 5,
   "Cuero Endurecido (ce)": 5,
   "Cota de Malla (cm)": 5,
   "Coraza (co)": 0,
   "Bonificación Defensiva": 15,
   "Arma principal": 115,
   "Arma secundaria": 96,
   "Arma terciaria": 97,
   "Arma cuarta": 57,
   "Trepar": 34,
   "Montar": 54,
   "Nadar": 24,
   "Rastrear": 34,
   "Emboscar": 2,
   "Acechar-Sigilo": 25,
   "Abrir Cerraduras": 25,
   "Desactivar Trampas": 25,
   "Leer Runas": 10,
   "Usar Objetos": 5,
   "Hechizos dirigidos": -15,
   "Percepción": 25,
   "totalPv": 121,
   "Hechizos básicos": 0,
   "Listas de hechizos": 0,
   "Oficio": 0,
   "name": "guerrero"
 },
 {
   "nivel": 10,
   "Sin Armadura (sa)": 20,
   "Cuero (cu)": 10,
   "Cuero Endurecido (ce)": 5,
   "Cota de Malla (cm)": 5,
   "Coraza (co)": 0,
   "Bonificación Defensiva": 15,
   "Arma principal": 120,
   "Arma secundaria": 101,
   "Arma terciaria": 100,
   "Arma cuarta": 65,
   "Trepar": 40,
   "Montar": 60,
   "Nadar": 25,
   "Rastrear": 35,
   "Emboscar": 2,
   "Acechar-Sigilo": 30,
   "Abrir Cerraduras": 25,
   "Desactivar Trampas": 25,
   "Leer Runas": 10,
   "Usar Objetos": 10,
   "Hechizos dirigidos": -15,
   "Percepción": 30,
   "totalPv": 129,
   "Hechizos básicos": 0,
   "Listas de hechizos": 0,
   "Oficio": 0,
   "name": "guerrero"
 },
 {
   "nivel": 1,
   "Sin Armadura (sa)": 25,
   "Cuero (cu)": 5,
   "Cuero Endurecido (ce)": -10,
   "Cota de Malla (cm)": -30,
   "Coraza (co)": -75,
   "Bonificación Defensiva": 20,
   "Arma principal": 41,
   "Arma secundaria": 31,
   "Arma terciaria": 21,
   "Arma cuarta": -10,
   "Trepar": 21,
   "Montar": 6,
   "Nadar": 21,
   "Rastrear": 6,
   "Emboscar": 1,
   "Acechar-Sigilo": 12,
   "Abrir Cerraduras": 7,
   "Desactivar Trampas": 7,
   "Leer Runas": -25,
   "Usar Objetos": -25,
   "Hechizos dirigidos": -10,
   "Percepción": 13,
   "totalPv": 27,
   "Hechizos básicos": 0,
   "Listas de hechizos": 0,
   "Oficio": 0,
   "name": "explorador"
 },
 {
   "nivel": 2,
   "Sin Armadura (sa)": 25,
   "Cuero (cu)": 5,
   "Cuero Endurecido (ce)": -5,
   "Cota de Malla (cm)": -30,
   "Coraza (co)": -75,
   "Bonificación Defensiva": 20,
   "Arma principal": 52,
   "Arma secundaria": 37,
   "Arma terciaria": 22,
   "Arma cuarta": -10,
   "Trepar": 27,
   "Montar": 12,
   "Nadar": 22,
   "Rastrear": 12,
   "Emboscar": 2,
   "Acechar-Sigilo": 19,
   "Abrir Cerraduras": 14,
   "Desactivar Trampas": 14,
   "Leer Runas": -25,
   "Usar Objetos": -25,
   "Hechizos dirigidos": -10,
   "Percepción": 21,
   "totalPv": 32,
   "Hechizos básicos": 0,
   "Listas de hechizos": 0,
   "Oficio": 0,
   "name": "explorador"
 },
 {
   "nivel": 3,
   "Sin Armadura (sa)": 25,
   "Cuero (cu)": 5,
   "Cuero Endurecido (ce)": 0,
   "Cota de Malla (cm)": -30,
   "Coraza (co)": -75,
   "Bonificación Defensiva": 20,
   "Arma principal": 63,
   "Arma secundaria": 43,
   "Arma terciaria": 23,
   "Arma cuarta": -10,
   "Trepar": 33,
   "Montar": 18,
   "Nadar": 23,
   "Rastrear": 18,
   "Emboscar": 3,
   "Acechar-Sigilo": 26,
   "Abrir Cerraduras": 21,
   "Desactivar Trampas": 21,
   "Leer Runas": -25,
   "Usar Objetos": -25,
   "Hechizos dirigidos": -10,
   "Percepción": 29,
   "totalPv": 38,
   "Hechizos básicos": 0,
   "Listas de hechizos": 0,
   "Oficio": 0,
   "name": "explorador"
 },
 {
   "nivel": 4,
   "Sin Armadura (sa)": 25,
   "Cuero (cu)": 5,
   "Cuero Endurecido (ce)": 5,
   "Cota de Malla (cm)": -30,
   "Coraza (co)": -75,
   "Bonificación Defensiva": 20,
   "Arma principal": 74,
   "Arma secundaria": 49,
   "Arma terciaria": 24,
   "Arma cuarta": -10,
   "Trepar": 39,
   "Montar": 24,
   "Nadar": 24,
   "Rastrear": 24,
   "Emboscar": 4,
   "Acechar-Sigilo": 28,
   "Abrir Cerraduras": 28,
   "Desactivar Trampas": 28,
   "Leer Runas": -25,
   "Usar Objetos": -25,
   "Hechizos dirigidos": -10,
   "Percepción": 37,
   "totalPv": 43,
   "Hechizos básicos": 0,
   "Listas de hechizos": 0,
   "Oficio": 0,
   "name": "explorador"
 },
 {
   "nivel": 5,
   "Sin Armadura (sa)": 25,
   "Cuero (cu)": 5,
   "Cuero Endurecido (ce)": 10,
   "Cota de Malla (cm)": -30,
   "Coraza (co)": -75,
   "Bonificación Defensiva": 20,
   "Arma principal": 80,
   "Arma secundaria": 55,
   "Arma terciaria": 30,
   "Arma cuarta": -10,
   "Trepar": 45,
   "Montar": 30,
   "Nadar": 25,
   "Rastrear": 25,
   "Emboscar": 5,
   "Acechar-Sigilo": 35,
   "Abrir Cerraduras": 35,
   "Desactivar Trampas": 35,
   "Leer Runas": 5,
   "Usar Objetos": -25,
   "Hechizos dirigidos": -10,
   "Percepción": 45,
   "totalPv": 49,
   "Hechizos básicos": 0,
   "Listas de hechizos": 0,
   "Oficio": 0,
   "name": "explorador"
 },
 {
   "nivel": 6,
   "Sin Armadura (sa)": 25,
   "Cuero (cu)": 5,
   "Cuero Endurecido (ce)": 10,
   "Cota de Malla (cm)": -25,
   "Coraza (co)": -75,
   "Bonificación Defensiva": 20,
   "Arma principal": 83,
   "Arma secundaria": 61,
   "Arma terciaria": 36,
   "Arma cuarta": -10,
   "Trepar": 51,
   "Montar": 36,
   "Nadar": 26,
   "Rastrear": 26,
   "Emboscar": 6,
   "Acechar-Sigilo": 42,
   "Abrir Cerraduras": 42,
   "Desactivar Trampas": 42,
   "Leer Runas": 5,
   "Usar Objetos": 5,
   "Hechizos dirigidos": -10,
   "Percepción": 48,
   "totalPv": 54,
   "Hechizos básicos": 0,
   "Listas de hechizos": 1,
   "Oficio": 0,
   "name": "explorador"
 },
 {
   "nivel": 7,
   "Sin Armadura (sa)": 25,
   "Cuero (cu)": 5,
   "Cuero Endurecido (ce)": 10,
   "Cota de Malla (cm)": -20,
   "Coraza (co)": -75,
   "Bonificación Defensiva": 20,
   "Arma principal": 86,
   "Arma secundaria": 67,
   "Arma terciaria": 42,
   "Arma cuarta": -10,
   "Trepar": 57,
   "Montar": 42,
   "Nadar": 27,
   "Rastrear": 27,
   "Emboscar": 7,
   "Acechar-Sigilo": 49,
   "Abrir Cerraduras": 49,
   "Desactivar Trampas": 49,
   "Leer Runas": 5,
   "Usar Objetos": 5,
   "Hechizos dirigidos": -10,
   "Percepción": 51,
   "totalPv": 60,
   "Hechizos básicos": 0,
   "Listas de hechizos": 1,
   "Oficio": 0,
   "name": "explorador"
 },
 {
   "nivel": 8,
   "Sin Armadura (sa)": 25,
   "Cuero (cu)": 5,
   "Cuero Endurecido (ce)": 10,
   "Cota de Malla (cm)": -15,
   "Coraza (co)": -75,
   "Bonificación Defensiva": 20,
   "Arma principal": 89,
   "Arma secundaria": 73,
   "Arma terciaria": 48,
   "Arma cuarta": -10,
   "Trepar": 63,
   "Montar": 48,
   "Nadar": 28,
   "Rastrear": 33,
   "Emboscar": 8,
   "Acechar-Sigilo": 56,
   "Abrir Cerraduras": 56,
   "Desactivar Trampas": 56,
   "Leer Runas": 5,
   "Usar Objetos": 5,
   "Hechizos dirigidos": -10,
   "Percepción": 59,
   "totalPv": 65,
   "Hechizos básicos": 0,
   "Listas de hechizos": 1,
   "Oficio": 0,
   "name": "explorador"
 },
 {
   "nivel": 9,
   "Sin Armadura (sa)": 25,
   "Cuero (cu)": 5,
   "Cuero Endurecido (ce)": 10,
   "Cota de Malla (cm)": -10,
   "Coraza (co)": -75,
   "Bonificación Defensiva": 20,
   "Arma principal": 92,
   "Arma secundaria": 79,
   "Arma terciaria": 54,
   "Arma cuarta": -10,
   "Trepar": 69,
   "Montar": 54,
   "Nadar": 29,
   "Rastrear": 39,
   "Emboscar": 9,
   "Acechar-Sigilo": 63,
   "Abrir Cerraduras": 63,
   "Desactivar Trampas": 63,
   "Leer Runas": 5,
   "Usar Objetos": 5,
   "Hechizos dirigidos": -10,
   "Percepción": 67,
   "totalPv": 71,
   "Hechizos básicos": 0,
   "Listas de hechizos": 1,
   "Oficio": 0,
   "name": "explorador"
 },
 {
   "nivel": 10,
   "Sin Armadura (sa)": 25,
   "Cuero (cu)": 5,
   "Cuero Endurecido (ce)": 10,
   "Cota de Malla (cm)": -5,
   "Coraza (co)": -75,
   "Bonificación Defensiva": 20,
   "Arma principal": 95,
   "Arma secundaria": 82,
   "Arma terciaria": 60,
   "Arma cuarta": -10,
   "Trepar": 75,
   "Montar": 60,
   "Nadar": 30,
   "Rastrear": 45,
   "Emboscar": 10,
   "Acechar-Sigilo": 70,
   "Abrir Cerraduras": 70,
   "Desactivar Trampas": 70,
   "Leer Runas": 5,
   "Usar Objetos": 5,
   "Hechizos dirigidos": -10,
   "Percepción": 75,
   "totalPv": 76,
   "Hechizos básicos": 0,
   "Listas de hechizos": 1,
   "Oficio": 0,
   "name": "explorador"
 },
 {
   "nivel": 1,
   "Sin Armadura (sa)": 15,
   "Cuero (cu)": -5,
   "Cuero Endurecido (ce)": -20,
   "Cota de Malla (cm)": -70,
   "Coraza (co)": -70,
   "Bonificación Defensiva": 5,
   "Arma principal": 15,
   "Arma secundaria": 15,
   "Arma terciaria": 10,
   "Arma cuarta": -25,
   "Trepar": 11,
   "Montar": 21,
   "Nadar": 11,
   "Rastrear": 11,
   "Emboscar": -50,
   "Acechar-Sigilo": 5,
   "Abrir Cerraduras": 10,
   "Desactivar Trampas": -10,
   "Leer Runas": 11,
   "Usar Objetos": 21,
   "Hechizos dirigidos": -18,
   "Percepción": 21,
   "totalPv": 16,
   "Hechizos básicos": 2,
   "Listas de hechizos": 2,
   "Oficio": 0,
   "name": "animista"
 },
 {
   "nivel": 2,
   "Sin Armadura (sa)": 15,
   "Cuero (cu)": -5,
   "Cuero Endurecido (ce)": -15,
   "Cota de Malla (cm)": -70,
   "Coraza (co)": -70,
   "Bonificación Defensiva": 6,
   "Arma principal": 20,
   "Arma secundaria": 20,
   "Arma terciaria": 10,
   "Arma cuarta": -25,
   "Trepar": 12,
   "Montar": 27,
   "Nadar": 12,
   "Rastrear": 12,
   "Emboscar": -50,
   "Acechar-Sigilo": 5,
   "Abrir Cerraduras": 10,
   "Desactivar Trampas": 20,
   "Leer Runas": 12,
   "Usar Objetos": 27,
   "Hechizos dirigidos": 14,
   "Percepción": 27,
   "totalPv": 22,
   "Hechizos básicos": 4,
   "Listas de hechizos": 3,
   "Oficio": 0,
   "name": "animista"
 },
 {
   "nivel": 3,
   "Sin Armadura (sa)": 15,
   "Cuero (cu)": -5,
   "Cuero Endurecido (ce)": -10,
   "Cota de Malla (cm)": -70,
   "Coraza (co)": -70,
   "Bonificación Defensiva": 7,
   "Arma principal": 25,
   "Arma secundaria": 25,
   "Arma terciaria": 10,
   "Arma cuarta": -25,
   "Trepar": 18,
   "Montar": 28,
   "Nadar": 13,
   "Rastrear": 13,
   "Emboscar": -50,
   "Acechar-Sigilo": 10,
   "Abrir Cerraduras": 10,
   "Desactivar Trampas": 20,
   "Leer Runas": 18,
   "Usar Objetos": 28,
   "Hechizos dirigidos": 21,
   "Percepción": 33,
   "totalPv": 27,
   "Hechizos básicos": 6,
   "Listas de hechizos": 4,
   "Oficio": 0,
   "name": "animista"
 },
 {
   "nivel": 4,
   "Sin Armadura (sa)": 15,
   "Cuero (cu)": -5,
   "Cuero Endurecido (ce)": -5,
   "Cota de Malla (cm)": -70,
   "Coraza (co)": -70,
   "Bonificación Defensiva": 8,
   "Arma principal": 30,
   "Arma secundaria": 30,
   "Arma terciaria": 10,
   "Arma cuarta": -25,
   "Trepar": 24,
   "Montar": 34,
   "Nadar": 14,
   "Rastrear": 14,
   "Emboscar": -50,
   "Acechar-Sigilo": 15,
   "Abrir Cerraduras": 10,
   "Desactivar Trampas": 20,
   "Leer Runas": 24,
   "Usar Objetos": 34,
   "Hechizos dirigidos": 23,
   "Percepción": 34,
   "totalPv": 33,
   "Hechizos básicos": 8,
   "Listas de hechizos": 5,
   "Oficio": 0,
   "name": "animista"
 },
 {
   "nivel": 5,
   "Sin Armadura (sa)": 15,
   "Cuero (cu)": -5,
   "Cuero Endurecido (ce)": 0,
   "Cota de Malla (cm)": -70,
   "Coraza (co)": -70,
   "Bonificación Defensiva": 9,
   "Arma principal": 35,
   "Arma secundaria": 35,
   "Arma terciaria": 10,
   "Arma cuarta": -25,
   "Trepar": 25,
   "Montar": 40,
   "Nadar": 15,
   "Rastrear": 15,
   "Emboscar": -50,
   "Acechar-Sigilo": 20,
   "Abrir Cerraduras": 10,
   "Desactivar Trampas": 20,
   "Leer Runas": 30,
   "Usar Objetos": 40,
   "Hechizos dirigidos": 25,
   "Percepción": 40,
   "totalPv": 38,
   "Hechizos básicos": 10,
   "Listas de hechizos": 6,
   "Oficio": 0,
   "name": "animista"
 },
 {
   "nivel": 6,
   "Sin Armadura (sa)": 15,
   "Cuero (cu)": 0,
   "Cuero Endurecido (ce)": 0,
   "Cota de Malla (cm)": -70,
   "Coraza (co)": -70,
   "Bonificación Defensiva": 10,
   "Arma principal": 40,
   "Arma secundaria": 40,
   "Arma terciaria": 10,
   "Arma cuarta": -25,
   "Trepar": 31,
   "Montar": 41,
   "Nadar": 16,
   "Rastrear": 16,
   "Emboscar": -50,
   "Acechar-Sigilo": 25,
   "Abrir Cerraduras": 10,
   "Desactivar Trampas": 20,
   "Leer Runas": 36,
   "Usar Objetos": 46,
   "Hechizos dirigidos": 27,
   "Percepción": 46,
   "totalPv": 44,
   "Hechizos básicos": 12,
   "Listas de hechizos": 7,
   "Oficio": 0,
   "name": "animista"
 },
 {
   "nivel": 7,
   "Sin Armadura (sa)": 15,
   "Cuero (cu)": 5,
   "Cuero Endurecido (ce)": 0,
   "Cota de Malla (cm)": -70,
   "Coraza (co)": -70,
   "Bonificación Defensiva": 11,
   "Arma principal": 45,
   "Arma secundaria": 45,
   "Arma terciaria": 10,
   "Arma cuarta": -25,
   "Trepar": 37,
   "Montar": 47,
   "Nadar": 17,
   "Rastrear": 17,
   "Emboscar": -50,
   "Acechar-Sigilo": 30,
   "Abrir Cerraduras": 10,
   "Desactivar Trampas": 20,
   "Leer Runas": 42,
   "Usar Objetos": 52,
   "Hechizos dirigidos": 29,
   "Percepción": 47,
   "totalPv": 49,
   "Hechizos básicos": 14,
   "Listas de hechizos": 8,
   "Oficio": 0,
   "name": "animista"
 },
 {
   "nivel": 8,
   "Sin Armadura (sa)": 15,
   "Cuero (cu)": 5,
   "Cuero Endurecido (ce)": 0,
   "Cota de Malla (cm)": -70,
   "Coraza (co)": -70,
   "Bonificación Defensiva": 12,
   "Arma principal": 50,
   "Arma secundaria": 50,
   "Arma terciaria": 10,
   "Arma cuarta": -25,
   "Trepar": 38,
   "Montar": 53,
   "Nadar": 18,
   "Rastrear": 18,
   "Emboscar": -50,
   "Acechar-Sigilo": 35,
   "Abrir Cerraduras": 10,
   "Desactivar Trampas": 20,
   "Leer Runas": 48,
   "Usar Objetos": 58,
   "Hechizos dirigidos": 31,
   "Percepción": 53,
   "totalPv": 55,
   "Hechizos básicos": 16,
   "Listas de hechizos": 9,
   "Oficio": 0,
   "name": "animista"
 },
 {
   "nivel": 9,
   "Sin Armadura (sa)": 15,
   "Cuero (cu)": 5,
   "Cuero Endurecido (ce)": 0,
   "Cota de Malla (cm)": -70,
   "Coraza (co)": -70,
   "Bonificación Defensiva": 13,
   "Arma principal": 55,
   "Arma secundaria": 55,
   "Arma terciaria": 10,
   "Arma cuarta": -25,
   "Trepar": 44,
   "Montar": 59,
   "Nadar": 19,
   "Rastrear": 19,
   "Emboscar": -50,
   "Acechar-Sigilo": 40,
   "Abrir Cerraduras": 10,
   "Desactivar Trampas": 20,
   "Leer Runas": 54,
   "Usar Objetos": 64,
   "Hechizos dirigidos": 33,
   "Percepción": 59,
   "totalPv": 60,
   "Hechizos básicos": 18,
   "Listas de hechizos": 10,
   "Oficio": 0,
   "name": "animista"
 },
 {
   "nivel": 10,
   "Sin Armadura (sa)": 15,
   "Cuero (cu)": 5,
   "Cuero Endurecido (ce)": 0,
   "Cota de Malla (cm)": -70,
   "Coraza (co)": -70,
   "Bonificación Defensiva": 14,
   "Arma principal": 57,
   "Arma secundaria": 57,
   "Arma terciaria": 10,
   "Arma cuarta": -25,
   "Trepar": 50,
   "Montar": 65,
   "Nadar": 20,
   "Rastrear": 20,
   "Emboscar": -50,
   "Acechar-Sigilo": 45,
   "Abrir Cerraduras": 10,
   "Desactivar Trampas": 20,
   "Leer Runas": 60,
   "Usar Objetos": 70,
   "Hechizos dirigidos": 35,
   "Percepción": 65,
   "totalPv": 66,
   "Hechizos básicos": 20,
   "Listas de hechizos": 11,
   "Oficio": 0,
   "name": "animista"
 },
 {
   "nivel": 1,
   "Sin Armadura (sa)": 10,
   "Cuero (cu)": -35,
   "Cuero Endurecido (ce)": -50,
   "Cota de Malla (cm)": -70,
   "Coraza (co)": -85,
   "Bonificación Defensiva": 5,
   "Arma principal": 11,
   "Arma secundaria": 16,
   "Arma terciaria": -25,
   "Arma cuarta": -25,
   "Trepar": 6,
   "Montar": 6,
   "Nadar": 6,
   "Rastrear": 11,
   "Emboscar": -40,
   "Acechar-Sigilo": 16,
   "Abrir Cerraduras": 16,
   "Desactivar Trampas": -19,
   "Leer Runas": 21,
   "Usar Objetos": 16,
   "Hechizos dirigidos": -19,
   "Percepción": 16,
   "totalPv": 16,
   "Hechizos básicos": 1,
   "Listas de hechizos": 1,
   "Oficio": 0,
   "name": "bardo"
 },
 {
   "nivel": 2,
   "Sin Armadura (sa)": 10,
   "Cuero (cu)": -35,
   "Cuero Endurecido (ce)": -50,
   "Cota de Malla (cm)": -70,
   "Coraza (co)": -85,
   "Bonificación Defensiva": 6,
   "Arma principal": 17,
   "Arma secundaria": 22,
   "Arma terciaria": -25,
   "Arma cuarta": -25,
   "Trepar": 7,
   "Montar": 12,
   "Nadar": 7,
   "Rastrear": 12,
   "Emboscar": -40,
   "Acechar-Sigilo": 17,
   "Abrir Cerraduras": 22,
   "Desactivar Trampas": 12,
   "Leer Runas": 27,
   "Usar Objetos": 22,
   "Hechizos dirigidos": -18,
   "Percepción": 22,
   "totalPv": 22,
   "Hechizos básicos": 2,
   "Listas de hechizos": 2,
   "Oficio": 0,
   "name": "bardo"
 },
 {
   "nivel": 3,
   "Sin Armadura (sa)": 10,
   "Cuero (cu)": -35,
   "Cuero Endurecido (ce)": -50,
   "Cota de Malla (cm)": -70,
   "Coraza (co)": -85,
   "Bonificación Defensiva": 7,
   "Arma principal": 23,
   "Arma secundaria": 28,
   "Arma terciaria": -25,
   "Arma cuarta": -25,
   "Trepar": 13,
   "Montar": 13,
   "Nadar": 8,
   "Rastrear": 13,
   "Emboscar": -40,
   "Acechar-Sigilo": 23,
   "Abrir Cerraduras": 23,
   "Desactivar Trampas": 18,
   "Leer Runas": 33,
   "Usar Objetos": 28,
   "Hechizos dirigidos": 13,
   "Percepción": 28,
   "totalPv": 27,
   "Hechizos básicos": 3,
   "Listas de hechizos": 3,
   "Oficio": 0,
   "name": "bardo"
 },
 {
   "nivel": 4,
   "Sin Armadura (sa)": 10,
   "Cuero (cu)": -35,
   "Cuero Endurecido (ce)": -50,
   "Cota de Malla (cm)": -70,
   "Coraza (co)": -85,
   "Bonificación Defensiva": 8,
   "Arma principal": 29,
   "Arma secundaria": 34,
   "Arma terciaria": -25,
   "Arma cuarta": -25,
   "Trepar": 19,
   "Montar": 19,
   "Nadar": 9,
   "Rastrear": 14,
   "Emboscar": -40,
   "Acechar-Sigilo": 29,
   "Abrir Cerraduras": 29,
   "Desactivar Trampas": 19,
   "Leer Runas": 39,
   "Usar Objetos": 34,
   "Hechizos dirigidos": 14,
   "Percepción": 34,
   "totalPv": 33,
   "Hechizos básicos": 4,
   "Listas de hechizos": 3,
   "Oficio": 0,
   "name": "bardo"
 },
 {
   "nivel": 5,
   "Sin Armadura (sa)": 10,
   "Cuero (cu)": -35,
   "Cuero Endurecido (ce)": -50,
   "Cota de Malla (cm)": -70,
   "Coraza (co)": -85,
   "Bonificación Defensiva": 9,
   "Arma principal": 35,
   "Arma secundaria": 40,
   "Arma terciaria": -25,
   "Arma cuarta": -25,
   "Trepar": 25,
   "Montar": 25,
   "Nadar": 10,
   "Rastrear": 15,
   "Emboscar": -40,
   "Acechar-Sigilo": 30,
   "Abrir Cerraduras": 30,
   "Desactivar Trampas": 25,
   "Leer Runas": 45,
   "Usar Objetos": 40,
   "Hechizos dirigidos": 15,
   "Percepción": 40,
   "totalPv": 38,
   "Hechizos básicos": 5,
   "Listas de hechizos": 4,
   "Oficio": 0,
   "name": "bardo"
 },
 {
   "nivel": 6,
   "Sin Armadura (sa)": 10,
   "Cuero (cu)": -35,
   "Cuero Endurecido (ce)": -50,
   "Cota de Malla (cm)": -70,
   "Coraza (co)": -85,
   "Bonificación Defensiva": 10,
   "Arma principal": 41,
   "Arma secundaria": 46,
   "Arma terciaria": -25,
   "Arma cuarta": -25,
   "Trepar": 31,
   "Montar": 31,
   "Nadar": 11,
   "Rastrear": 16,
   "Emboscar": -40,
   "Acechar-Sigilo": 36,
   "Abrir Cerraduras": 36,
   "Desactivar Trampas": 31,
   "Leer Runas": 51,
   "Usar Objetos": 46,
   "Hechizos dirigidos": 16,
   "Percepción": 46,
   "totalPv": 44,
   "Hechizos básicos": 6,
   "Listas de hechizos": 5,
   "Oficio": 0,
   "name": "bardo"
 },
 {
   "nivel": 7,
   "Sin Armadura (sa)": 10,
   "Cuero (cu)": -35,
   "Cuero Endurecido (ce)": -50,
   "Cota de Malla (cm)": -70,
   "Coraza (co)": -85,
   "Bonificación Defensiva": 11,
   "Arma principal": 47,
   "Arma secundaria": 52,
   "Arma terciaria": -25,
   "Arma cuarta": -25,
   "Trepar": 37,
   "Montar": 37,
   "Nadar": 12,
   "Rastrear": 17,
   "Emboscar": -40,
   "Acechar-Sigilo": 42,
   "Abrir Cerraduras": 42,
   "Desactivar Trampas": 32,
   "Leer Runas": 57,
   "Usar Objetos": 52,
   "Hechizos dirigidos": 17,
   "Percepción": 52,
   "totalPv": 49,
   "Hechizos básicos": 7,
   "Listas de hechizos": 5,
   "Oficio": 0,
   "name": "bardo"
 },
 {
   "nivel": 8,
   "Sin Armadura (sa)": 10,
   "Cuero (cu)": -35,
   "Cuero Endurecido (ce)": -50,
   "Cota de Malla (cm)": -70,
   "Coraza (co)": -85,
   "Bonificación Defensiva": 12,
   "Arma principal": 53,
   "Arma secundaria": 58,
   "Arma terciaria": -25,
   "Arma cuarta": -25,
   "Trepar": 43,
   "Montar": 43,
   "Nadar": 13,
   "Rastrear": 18,
   "Emboscar": -40,
   "Acechar-Sigilo": 43,
   "Abrir Cerraduras": 43,
   "Desactivar Trampas": 38,
   "Leer Runas": 63,
   "Usar Objetos": 58,
   "Hechizos dirigidos": 18,
   "Percepción": 58,
   "totalPv": 55,
   "Hechizos básicos": 8,
   "Listas de hechizos": 6,
   "Oficio": 0,
   "name": "bardo"
 },
 {
   "nivel": 9,
   "Sin Armadura (sa)": 10,
   "Cuero (cu)": -35,
   "Cuero Endurecido (ce)": -50,
   "Cota de Malla (cm)": -70,
   "Coraza (co)": -85,
   "Bonificación Defensiva": 13,
   "Arma principal": 59,
   "Arma secundaria": 64,
   "Arma terciaria": -25,
   "Arma cuarta": -25,
   "Trepar": 49,
   "Montar": 49,
   "Nadar": 14,
   "Rastrear": 19,
   "Emboscar": -40,
   "Acechar-Sigilo": 49,
   "Abrir Cerraduras": 49,
   "Desactivar Trampas": 44,
   "Leer Runas": 69,
   "Usar Objetos": 64,
   "Hechizos dirigidos": 19,
   "Percepción": 64,
   "totalPv": 60,
   "Hechizos básicos": 9,
   "Listas de hechizos": 7,
   "Oficio": 0,
   "name": "bardo"
 },
 {
   "nivel": 10,
   "Sin Armadura (sa)": 10,
   "Cuero (cu)": -35,
   "Cuero Endurecido (ce)": -50,
   "Cota de Malla (cm)": -70,
   "Coraza (co)": -85,
   "Bonificación Defensiva": 14,
   "Arma principal": 62,
   "Arma secundaria": 67,
   "Arma terciaria": -25,
   "Arma cuarta": -25,
   "Trepar": 55,
   "Montar": 55,
   "Nadar": 15,
   "Rastrear": 20,
   "Emboscar": -40,
   "Acechar-Sigilo": 55,
   "Abrir Cerraduras": 55,
   "Desactivar Trampas": 45,
   "Leer Runas": 72,
   "Usar Objetos": 67,
   "Hechizos dirigidos": 20,
   "Percepción": 67,
   "totalPv": 66,
   "Hechizos básicos": 10,
   "Listas de hechizos": 8,
   "Oficio": 0,
   "name": "bardo"
 },
 {
   "nivel": 1,
   "Sin Armadura (sa)": 10,
   "Cuero (cu)": -5,
   "Cuero Endurecido (ce)": -10,
   "Cota de Malla (cm)": -30,
   "Coraza (co)": -75,
   "Bonificación Defensiva": 10,
   "Arma principal": 42,
   "Arma secundaria": 22,
   "Arma terciaria": 17,
   "Arma cuarta": -8,
   "Trepar": 13,
   "Montar": 18,
   "Nadar": 13,
   "Rastrear": 8,
   "Emboscar": -25,
   "Acechar-Sigilo": 12,
   "Abrir Cerraduras": 5,
   "Desactivar Trampas": 20,
   "Leer Runas": -25,
   "Usar Objetos": -20,
   "Hechizos dirigidos": -20,
   "Percepción": 12,
   "totalPv": 32,
   "Hechizos básicos": 0,
   "Listas de hechizos": 0,
   "Oficio": 0,
   "name": "montaraz"
 },
 {
   "nivel": 2,
   "Sin Armadura (sa)": 10,
   "Cuero (cu)": -5,
   "Cuero Endurecido (ce)": 0,
   "Cota de Malla (cm)": -30,
   "Coraza (co)": -75,
   "Bonificación Defensiva": 11,
   "Arma principal": 54,
   "Arma secundaria": 29,
   "Arma terciaria": 19,
   "Arma cuarta": -6,
   "Trepar": 21,
   "Montar": 26,
   "Nadar": 16,
   "Rastrear": 16,
   "Emboscar": -25,
   "Acechar-Sigilo": 19,
   "Abrir Cerraduras": 5,
   "Desactivar Trampas": 10,
   "Leer Runas": -25,
   "Usar Objetos": -20,
   "Hechizos dirigidos": -20,
   "Percepción": 19,
   "totalPv": 37,
   "Hechizos básicos": 0,
   "Listas de hechizos": 1,
   "Oficio": 0,
   "name": "montaraz"
 },
 {
   "nivel": 3,
   "Sin Armadura (sa)": 15,
   "Cuero (cu)": 0,
   "Cuero Endurecido (ce)": 0,
   "Cota de Malla (cm)": -30,
   "Coraza (co)": -75,
   "Bonificación Defensiva": 12,
   "Arma principal": 66,
   "Arma secundaria": 36,
   "Arma terciaria": 21,
   "Arma cuarta": -4,
   "Trepar": 29,
   "Montar": 34,
   "Nadar": 19,
   "Rastrear": 24,
   "Emboscar": 1,
   "Acechar-Sigilo": 26,
   "Abrir Cerraduras": 5,
   "Desactivar Trampas": 10,
   "Leer Runas": -25,
   "Usar Objetos": -20,
   "Hechizos dirigidos": -20,
   "Percepción": 26,
   "totalPv": 43,
   "Hechizos básicos": 0,
   "Listas de hechizos": 1,
   "Oficio": 0,
   "name": "montaraz"
 },
 {
   "nivel": 4,
   "Sin Armadura (sa)": 15,
   "Cuero (cu)": 5,
   "Cuero Endurecido (ce)": 0,
   "Cota de Malla (cm)": -25,
   "Coraza (co)": -75,
   "Bonificación Defensiva": 13,
   "Arma principal": 78,
   "Arma secundaria": 43,
   "Arma terciaria": 23,
   "Arma cuarta": -2,
   "Trepar": 37,
   "Montar": 42,
   "Nadar": 22,
   "Rastrear": 32,
   "Emboscar": 2,
   "Acechar-Sigilo": 33,
   "Abrir Cerraduras": 5,
   "Desactivar Trampas": 10,
   "Leer Runas": -25,
   "Usar Objetos": -20,
   "Hechizos dirigidos": -20,
   "Percepción": 33,
   "totalPv": 48,
   "Hechizos básicos": 0,
   "Listas de hechizos": 1,
   "Oficio": 0,
   "name": "montaraz"
 },
 {
   "nivel": 5,
   "Sin Armadura (sa)": 15,
   "Cuero (cu)": 5,
   "Cuero Endurecido (ce)": 0,
   "Cota de Malla (cm)": -20,
   "Coraza (co)": -75,
   "Bonificación Defensiva": 14,
   "Arma principal": 85,
   "Arma secundaria": 50,
   "Arma terciaria": 30,
   "Arma cuarta": 0,
   "Trepar": 45,
   "Montar": 50,
   "Nadar": 25,
   "Rastrear": 40,
   "Emboscar": 2,
   "Acechar-Sigilo": 40,
   "Abrir Cerraduras": 5,
   "Desactivar Trampas": 10,
   "Leer Runas": 5,
   "Usar Objetos": -20,
   "Hechizos dirigidos": -20,
   "Percepción": 40,
   "totalPv": 54,
   "Hechizos básicos": 0,
   "Listas de hechizos": 2,
   "Oficio": 0,
   "name": "montaraz"
 },
 {
   "nivel": 6,
   "Sin Armadura (sa)": 15,
   "Cuero (cu)": 5,
   "Cuero Endurecido (ce)": 0,
   "Cota de Malla (cm)": -15,
   "Coraza (co)": -75,
   "Bonificación Defensiva": 15,
   "Arma principal": 89,
   "Arma secundaria": 57,
   "Arma terciaria": 37,
   "Arma cuarta": 2,
   "Trepar": 53,
   "Montar": 58,
   "Nadar": 28,
   "Rastrear": 48,
   "Emboscar": 2,
   "Acechar-Sigilo": 47,
   "Abrir Cerraduras": 5,
   "Desactivar Trampas": 10,
   "Leer Runas": 5,
   "Usar Objetos": 10,
   "Hechizos dirigidos": -20,
   "Percepción": 47,
   "totalPv": 59,
   "Hechizos básicos": 0,
   "Listas de hechizos": 2,
   "Oficio": 0,
   "name": "montaraz"
 },
 {
   "nivel": 7,
   "Sin Armadura (sa)": 15,
   "Cuero (cu)": 5,
   "Cuero Endurecido (ce)": 0,
   "Cota de Malla (cm)": -5,
   "Coraza (co)": -75,
   "Bonificación Defensiva": 16,
   "Arma principal": 93,
   "Arma secundaria": 64,
   "Arma terciaria": 44,
   "Arma cuarta": 4,
   "Trepar": 61,
   "Montar": 66,
   "Nadar": 31,
   "Rastrear": 56,
   "Emboscar": 3,
   "Acechar-Sigilo": 54,
   "Abrir Cerraduras": 5,
   "Desactivar Trampas": 10,
   "Leer Runas": 5,
   "Usar Objetos": 10,
   "Hechizos dirigidos": -20,
   "Percepción": 54,
   "totalPv": 65,
   "Hechizos básicos": 0,
   "Listas de hechizos": 3,
   "Oficio": 0,
   "name": "montaraz"
 },
 {
   "nivel": 8,
   "Sin Armadura (sa)": 15,
   "Cuero (cu)": 5,
   "Cuero Endurecido (ce)": 0,
   "Cota de Malla (cm)": 0,
   "Coraza (co)": -45,
   "Bonificación Defensiva": 17,
   "Arma principal": 97,
   "Arma secundaria": 71,
   "Arma terciaria": 51,
   "Arma cuarta": 6,
   "Trepar": 69,
   "Montar": 74,
   "Nadar": 34,
   "Rastrear": 64,
   "Emboscar": 4,
   "Acechar-Sigilo": 61,
   "Abrir Cerraduras": 5,
   "Desactivar Trampas": 10,
   "Leer Runas": 5,
   "Usar Objetos": 10,
   "Hechizos dirigidos": -20,
   "Percepción": 61,
   "totalPv": 70,
   "Hechizos básicos": 0,
   "Listas de hechizos": 4,
   "Oficio": 0,
   "name": "montaraz"
 },
 {
   "nivel": 9,
   "Sin Armadura (sa)": 15,
   "Cuero (cu)": 5,
   "Cuero Endurecido (ce)": 0,
   "Cota de Malla (cm)": 0,
   "Coraza (co)": -35,
   "Bonificación Defensiva": 18,
   "Arma principal": 101,
   "Arma secundaria": 78,
   "Arma terciaria": 58,
   "Arma cuarta": 8,
   "Trepar": 77,
   "Montar": 82,
   "Nadar": 37,
   "Rastrear": 72,
   "Emboscar": 5,
   "Acechar-Sigilo": 68,
   "Abrir Cerraduras": 5,
   "Desactivar Trampas": 10,
   "Leer Runas": 5,
   "Usar Objetos": 10,
   "Hechizos dirigidos": -20,
   "Percepción": 68,
   "totalPv": 76,
   "Hechizos básicos": 0,
   "Listas de hechizos": 4,
   "Oficio": 0,
   "name": "montaraz"
 },
 {
   "nivel": 10,
   "Sin Armadura (sa)": 15,
   "Cuero (cu)": 5,
   "Cuero Endurecido (ce)": 0,
   "Cota de Malla (cm)": 0,
   "Coraza (co)": -25,
   "Bonificación Defensiva": 19,
   "Arma principal": 105,
   "Arma secundaria": 82,
   "Arma terciaria": 65,
   "Arma cuarta": 10,
   "Trepar": 85,
   "Montar": 87,
   "Nadar": 40,
   "Rastrear": 80,
   "Emboscar": 6,
   "Acechar-Sigilo": 72,
   "Abrir Cerraduras": 5,
   "Desactivar Trampas": 10,
   "Leer Runas": 5,
   "Usar Objetos": 10,
   "Hechizos dirigidos": -20,
   "Percepción": 72,
   "totalPv": 81,
   "Hechizos básicos": 0,
   "Listas de hechizos": 5,
   "Oficio": 0,
   "name": "montaraz"
 },
 {
   "nivel": 1,
   "Sin Armadura (sa)": 10,
   "Cuero (cu)": -70,
   "Cuero Endurecido (ce)": -70,
   "Cota de Malla (cm)": -70,
   "Coraza (co)": -70,
   "Bonificación Defensiva": 5,
   "Arma principal": 5,
   "Arma secundaria": 10,
   "Arma terciaria": -25,
   "Arma cuarta": -25,
   "Trepar": 10,
   "Montar": 10,
   "Nadar": 10,
   "Rastrear": 20,
   "Emboscar": -50,
   "Acechar-Sigilo": -20,
   "Abrir Cerraduras": -10,
   "Desactivar Trampas": -20,
   "Leer Runas": 27,
   "Usar Objetos": 17,
   "Hechizos dirigidos": 18,
   "Percepción": 15,
   "totalPv": 16,
   "Hechizos básicos": 2,
   "Listas de hechizos": 2,
   "Oficio": 0,
   "name": "mago"
 },
 {
   "nivel": 2,
   "Sin Armadura (sa)": 10,
   "Cuero (cu)": -70,
   "Cuero Endurecido (ce)": -70,
   "Cota de Malla (cm)": -70,
   "Coraza (co)": -70,
   "Bonificación Defensiva": 5,
   "Arma principal": 5,
   "Arma secundaria": 10,
   "Arma terciaria": -25,
   "Arma cuarta": -25,
   "Trepar": 10,
   "Montar": 10,
   "Nadar": 10,
   "Rastrear": 20,
   "Emboscar": -50,
   "Acechar-Sigilo": -20,
   "Abrir Cerraduras": -10,
   "Desactivar Trampas": -20,
   "Leer Runas": 34,
   "Usar Objetos": 24,
   "Hechizos dirigidos": 31,
   "Percepción": 15,
   "totalPv": 22,
   "Hechizos básicos": 4,
   "Listas de hechizos": 3,
   "Oficio": 0,
   "name": "mago"
 },
 {
   "nivel": 3,
   "Sin Armadura (sa)": 10,
   "Cuero (cu)": -70,
   "Cuero Endurecido (ce)": -70,
   "Cota de Malla (cm)": -70,
   "Coraza (co)": -70,
   "Bonificación Defensiva": 5,
   "Arma principal": 5,
   "Arma secundaria": 10,
   "Arma terciaria": -25,
   "Arma cuarta": -25,
   "Trepar": 10,
   "Montar": 10,
   "Nadar": 10,
   "Rastrear": 20,
   "Emboscar": -50,
   "Acechar-Sigilo": 10,
   "Abrir Cerraduras": -10,
   "Desactivar Trampas": -20,
   "Leer Runas": 41,
   "Usar Objetos": 31,
   "Hechizos dirigidos": 44,
   "Percepción": 15,
   "totalPv": 27,
   "Hechizos básicos": 6,
   "Listas de hechizos": 5,
   "Oficio": 0,
   "name": "mago"
 },
 {
   "nivel": 4,
   "Sin Armadura (sa)": 10,
   "Cuero (cu)": -70,
   "Cuero Endurecido (ce)": -70,
   "Cota de Malla (cm)": -70,
   "Coraza (co)": -70,
   "Bonificación Defensiva": 5,
   "Arma principal": 5,
   "Arma secundaria": 10,
   "Arma terciaria": -25,
   "Arma cuarta": -25,
   "Trepar": 10,
   "Montar": 10,
   "Nadar": 10,
   "Rastrear": 20,
   "Emboscar": -50,
   "Acechar-Sigilo": 10,
   "Abrir Cerraduras": 10,
   "Desactivar Trampas": -20,
   "Leer Runas": 48,
   "Usar Objetos": 38,
   "Hechizos dirigidos": 57,
   "Percepción": 15,
   "totalPv": 33,
   "Hechizos básicos": 8,
   "Listas de hechizos": 6,
   "Oficio": 0,
   "name": "mago"
 },
 {
   "nivel": 5,
   "Sin Armadura (sa)": 10,
   "Cuero (cu)": -70,
   "Cuero Endurecido (ce)": -70,
   "Cota de Malla (cm)": -70,
   "Coraza (co)": -70,
   "Bonificación Defensiva": 5,
   "Arma principal": 5,
   "Arma secundaria": 10,
   "Arma terciaria": -25,
   "Arma cuarta": -25,
   "Trepar": 10,
   "Montar": 10,
   "Nadar": 10,
   "Rastrear": 20,
   "Emboscar": -50,
   "Acechar-Sigilo": 10,
   "Abrir Cerraduras": 20,
   "Desactivar Trampas": -20,
   "Leer Runas": 55,
   "Usar Objetos": 45,
   "Hechizos dirigidos": 70,
   "Percepción": 15,
   "totalPv": 38,
   "Hechizos básicos": 10,
   "Listas de hechizos": 7,
   "Oficio": 0,
   "name": "mago"
 },
 {
   "nivel": 6,
   "Sin Armadura (sa)": 10,
   "Cuero (cu)": -70,
   "Cuero Endurecido (ce)": -70,
   "Cota de Malla (cm)": -70,
   "Coraza (co)": -70,
   "Bonificación Defensiva": 5,
   "Arma principal": 5,
   "Arma secundaria": 10,
   "Arma terciaria": -25,
   "Arma cuarta": -25,
   "Trepar": 10,
   "Montar": 10,
   "Nadar": 10,
   "Rastrear": 20,
   "Emboscar": -50,
   "Acechar-Sigilo": 10,
   "Abrir Cerraduras": 20,
   "Desactivar Trampas": -20,
   "Leer Runas": 62,
   "Usar Objetos": 57,
   "Hechizos dirigidos": 75,
   "Percepción": 15,
   "totalPv": 44,
   "Hechizos básicos": 12,
   "Listas de hechizos": 9,
   "Oficio": 0,
   "name": "mago"
 },
 {
   "nivel": 7,
   "Sin Armadura (sa)": 10,
   "Cuero (cu)": -70,
   "Cuero Endurecido (ce)": -70,
   "Cota de Malla (cm)": -70,
   "Coraza (co)": -70,
   "Bonificación Defensiva": 5,
   "Arma principal": 5,
   "Arma secundaria": 10,
   "Arma terciaria": -25,
   "Arma cuarta": -25,
   "Trepar": 10,
   "Montar": 10,
   "Nadar": 10,
   "Rastrear": 20,
   "Emboscar": -50,
   "Acechar-Sigilo": 10,
   "Abrir Cerraduras": 20,
   "Desactivar Trampas": 10,
   "Leer Runas": 69,
   "Usar Objetos": 69,
   "Hechizos dirigidos": 80,
   "Percepción": 15,
   "totalPv": 49,
   "Hechizos básicos": 14,
   "Listas de hechizos": 10,
   "Oficio": 0,
   "name": "mago"
 },
 {
   "nivel": 8,
   "Sin Armadura (sa)": 10,
   "Cuero (cu)": -70,
   "Cuero Endurecido (ce)": -70,
   "Cota de Malla (cm)": -70,
   "Coraza (co)": -70,
   "Bonificación Defensiva": 5,
   "Arma principal": 5,
   "Arma secundaria": 10,
   "Arma terciaria": -25,
   "Arma cuarta": -25,
   "Trepar": 10,
   "Montar": 10,
   "Nadar": 10,
   "Rastrear": 20,
   "Emboscar": -50,
   "Acechar-Sigilo": 10,
   "Abrir Cerraduras": 20,
   "Desactivar Trampas": 10,
   "Leer Runas": 81,
   "Usar Objetos": 73,
   "Hechizos dirigidos": 85,
   "Percepción": 15,
   "totalPv": 55,
   "Hechizos básicos": 16,
   "Listas de hechizos": 11,
   "Oficio": 0,
   "name": "mago"
 },
 {
   "nivel": 9,
   "Sin Armadura (sa)": 10,
   "Cuero (cu)": -70,
   "Cuero Endurecido (ce)": -70,
   "Cota de Malla (cm)": -70,
   "Coraza (co)": -70,
   "Bonificación Defensiva": 5,
   "Arma principal": 5,
   "Arma secundaria": 10,
   "Arma terciaria": -25,
   "Arma cuarta": -25,
   "Trepar": 10,
   "Montar": 10,
   "Nadar": 10,
   "Rastrear": 20,
   "Emboscar": -50,
   "Acechar-Sigilo": 10,
   "Abrir Cerraduras": 20,
   "Desactivar Trampas": 10,
   "Leer Runas": 87,
   "Usar Objetos": 77,
   "Hechizos dirigidos": 90,
   "Percepción": 15,
   "totalPv": 60,
   "Hechizos básicos": 18,
   "Listas de hechizos": 13,
   "Oficio": 0,
   "name": "mago"
 },
 {
   "nivel": 10,
   "Sin Armadura (sa)": 10,
   "Cuero (cu)": -70,
   "Cuero Endurecido (ce)": -70,
   "Cota de Malla (cm)": -70,
   "Coraza (co)": -70,
   "Bonificación Defensiva": 5,
   "Arma principal": 5,
   "Arma secundaria": 10,
   "Arma terciaria": -25,
   "Arma cuarta": -25,
   "Trepar": 10,
   "Montar": 10,
   "Nadar": 10,
   "Rastrear": 20,
   "Emboscar": -50,
   "Acechar-Sigilo": 10,
   "Abrir Cerraduras": 20,
   "Desactivar Trampas": 10,
   "Leer Runas": 91,
   "Usar Objetos": 81,
   "Hechizos dirigidos": 95,
   "Percepción": 15,
   "totalPv": 66,
   "Hechizos básicos": 20,
   "Listas de hechizos": 14,
   "Oficio": 0,
   "name": "mago"
 },
 {
   "nivel": 1,
   "Sin Armadura (sa)": 10,
   "Cuero (cu)": -35,
   "Cuero Endurecido (ce)": -50,
   "Cota de Malla (cm)": -70,
   "Coraza (co)": -85,
   "Bonificación Defensiva": 5,
   "Arma principal": 5,
   "Arma secundaria": -25,
   "Arma terciaria": -25,
   "Arma cuarta": -25,
   "Trepar": 0,
   "Montar": 0,
   "Nadar": 0,
   "Rastrear": 0,
   "Emboscar": -40,
   "Acechar-Sigilo": 0,
   "Abrir Cerraduras": 0,
   "Desactivar Trampas": 0,
   "Leer Runas": -25,
   "Usar Objetos": -25,
   "Hechizos dirigidos": -25,
   "Percepción": 16,
   "totalPv": 16,
   "Hechizos básicos": 1,
   "Listas de hechizos": 0,
   "Oficio": 43,
   "name": "civil"
 },
 {
   "nivel": 2,
   "Sin Armadura (sa)": 10,
   "Cuero (cu)": -35,
   "Cuero Endurecido (ce)": -50,
   "Cota de Malla (cm)": -70,
   "Coraza (co)": -85,
   "Bonificación Defensiva": 5,
   "Arma principal": 7,
   "Arma secundaria": -25,
   "Arma terciaria": -25,
   "Arma cuarta": -25,
   "Trepar": 0,
   "Montar": 0,
   "Nadar": 0,
   "Rastrear": 0,
   "Emboscar": -40,
   "Acechar-Sigilo": 0,
   "Abrir Cerraduras": 0,
   "Desactivar Trampas": 0,
   "Leer Runas": -25,
   "Usar Objetos": -25,
   "Hechizos dirigidos": -25,
   "Percepción": 22,
   "totalPv": 22,
   "Hechizos básicos": 2,
   "Listas de hechizos": 0,
   "Oficio": 56,
   "name": "civil"
 },
 {
   "nivel": 3,
   "Sin Armadura (sa)": 10,
   "Cuero (cu)": -35,
   "Cuero Endurecido (ce)": -50,
   "Cota de Malla (cm)": -70,
   "Coraza (co)": -85,
   "Bonificación Defensiva": 5,
   "Arma principal": 9,
   "Arma secundaria": -25,
   "Arma terciaria": -25,
   "Arma cuarta": -25,
   "Trepar": 0,
   "Montar": 0,
   "Nadar": 0,
   "Rastrear": 0,
   "Emboscar": -40,
   "Acechar-Sigilo": 0,
   "Abrir Cerraduras": 0,
   "Desactivar Trampas": 0,
   "Leer Runas": -25,
   "Usar Objetos": -25,
   "Hechizos dirigidos": -25,
   "Percepción": 28,
   "totalPv": 27,
   "Hechizos básicos": 3,
   "Listas de hechizos": 0,
   "Oficio": 69,
   "name": "civil"
 },
 {
   "nivel": 4,
   "Sin Armadura (sa)": 10,
   "Cuero (cu)": -35,
   "Cuero Endurecido (ce)": -50,
   "Cota de Malla (cm)": -70,
   "Coraza (co)": -85,
   "Bonificación Defensiva": 5,
   "Arma principal": 12,
   "Arma secundaria": -25,
   "Arma terciaria": -25,
   "Arma cuarta": -25,
   "Trepar": 0,
   "Montar": 0,
   "Nadar": 0,
   "Rastrear": 0,
   "Emboscar": -40,
   "Acechar-Sigilo": 0,
   "Abrir Cerraduras": 0,
   "Desactivar Trampas": 0,
   "Leer Runas": -25,
   "Usar Objetos": -25,
   "Hechizos dirigidos": -25,
   "Percepción": 34,
   "totalPv": 33,
   "Hechizos básicos": 4,
   "Listas de hechizos": 0,
   "Oficio": 82,
   "name": "civil"
 },
 {
   "nivel": 5,
   "Sin Armadura (sa)": 10,
   "Cuero (cu)": -35,
   "Cuero Endurecido (ce)": -50,
   "Cota de Malla (cm)": -70,
   "Coraza (co)": -85,
   "Bonificación Defensiva": 5,
   "Arma principal": 15,
   "Arma secundaria": -25,
   "Arma terciaria": -25,
   "Arma cuarta": -25,
   "Trepar": 0,
   "Montar": 0,
   "Nadar": 0,
   "Rastrear": 0,
   "Emboscar": -40,
   "Acechar-Sigilo": 0,
   "Abrir Cerraduras": 0,
   "Desactivar Trampas": 0,
   "Leer Runas": -25,
   "Usar Objetos": -25,
   "Hechizos dirigidos": -25,
   "Percepción": 40,
   "totalPv": 38,
   "Hechizos básicos": 5,
   "Listas de hechizos": 0,
   "Oficio": 95,
   "name": "civil"
 },
 {
   "nivel": 6,
   "Sin Armadura (sa)": 10,
   "Cuero (cu)": -35,
   "Cuero Endurecido (ce)": -50,
   "Cota de Malla (cm)": -70,
   "Coraza (co)": -85,
   "Bonificación Defensiva": 5,
   "Arma principal": 20,
   "Arma secundaria": -25,
   "Arma terciaria": -25,
   "Arma cuarta": -25,
   "Trepar": 0,
   "Montar": 0,
   "Nadar": 0,
   "Rastrear": 0,
   "Emboscar": -40,
   "Acechar-Sigilo": 0,
   "Abrir Cerraduras": 0,
   "Desactivar Trampas": 0,
   "Leer Runas": -25,
   "Usar Objetos": -25,
   "Hechizos dirigidos": -25,
   "Percepción": 46,
   "totalPv": 44,
   "Hechizos básicos": 6,
   "Listas de hechizos": 0,
   "Oficio": 100,
   "name": "civil"
 },
 {
   "nivel": 7,
   "Sin Armadura (sa)": 10,
   "Cuero (cu)": -35,
   "Cuero Endurecido (ce)": -50,
   "Cota de Malla (cm)": -70,
   "Coraza (co)": -85,
   "Bonificación Defensiva": 5,
   "Arma principal": 22,
   "Arma secundaria": -25,
   "Arma terciaria": -25,
   "Arma cuarta": -25,
   "Trepar": 0,
   "Montar": 0,
   "Nadar": 0,
   "Rastrear": 0,
   "Emboscar": -40,
   "Acechar-Sigilo": 0,
   "Abrir Cerraduras": 0,
   "Desactivar Trampas": 0,
   "Leer Runas": -25,
   "Usar Objetos": -25,
   "Hechizos dirigidos": -25,
   "Percepción": 52,
   "totalPv": 49,
   "Hechizos básicos": 7,
   "Listas de hechizos": 0,
   "Oficio": 105,
   "name": "civil"
 },
 {
   "nivel": 8,
   "Sin Armadura (sa)": 10,
   "Cuero (cu)": -35,
   "Cuero Endurecido (ce)": -50,
   "Cota de Malla (cm)": -70,
   "Coraza (co)": -85,
   "Bonificación Defensiva": 5,
   "Arma principal": 25,
   "Arma secundaria": -25,
   "Arma terciaria": -25,
   "Arma cuarta": -25,
   "Trepar": 0,
   "Montar": 0,
   "Nadar": 0,
   "Rastrear": 0,
   "Emboscar": -40,
   "Acechar-Sigilo": 0,
   "Abrir Cerraduras": 0,
   "Desactivar Trampas": 0,
   "Leer Runas": -25,
   "Usar Objetos": -25,
   "Hechizos dirigidos": -25,
   "Percepción": 58,
   "totalPv": 55,
   "Hechizos básicos": 8,
   "Listas de hechizos": 0,
   "Oficio": 110,
   "name": "civil"
 },
 {
   "nivel": 9,
   "Sin Armadura (sa)": 10,
   "Cuero (cu)": -35,
   "Cuero Endurecido (ce)": -50,
   "Cota de Malla (cm)": -70,
   "Coraza (co)": -85,
   "Bonificación Defensiva": 5,
   "Arma principal": 30,
   "Arma secundaria": -25,
   "Arma terciaria": -25,
   "Arma cuarta": -25,
   "Trepar": 0,
   "Montar": 0,
   "Nadar": 0,
   "Rastrear": 0,
   "Emboscar": -40,
   "Acechar-Sigilo": 0,
   "Abrir Cerraduras": 0,
   "Desactivar Trampas": 0,
   "Leer Runas": -25,
   "Usar Objetos": -25,
   "Hechizos dirigidos": -25,
   "Percepción": 64,
   "totalPv": 60,
   "Hechizos básicos": 9,
   "Listas de hechizos": 0,
   "Oficio": 115,
   "name": "civil"
 },
 {
   "nivel": 10,
   "Sin Armadura (sa)": 10,
   "Cuero (cu)": -35,
   "Cuero Endurecido (ce)": -50,
   "Cota de Malla (cm)": -70,
   "Coraza (co)": -85,
   "Bonificación Defensiva": 5,
   "Arma principal": 35,
   "Arma secundaria": -25,
   "Arma terciaria": -25,
   "Arma cuarta": -25,
   "Trepar": 0,
   "Montar": 0,
   "Nadar": 0,
   "Rastrear": 0,
   "Emboscar": -40,
   "Acechar-Sigilo": 0,
   "Abrir Cerraduras": 0,
   "Desactivar Trampas": 0,
   "Leer Runas": -25,
   "Usar Objetos": -25,
   "Hechizos dirigidos": -25,
   "Percepción": 67,
   "totalPv": 66,
   "Hechizos básicos": 10,
   "Listas de hechizos": 0,
   "Oficio": 120,
   "name": "civil"
 }
]